cloudsnorkel/cdk_github_runners/__init__.py
cloudsnorkel/cdk_github_runners/py.typed
cloudsnorkel/cdk_github_runners/_jsii/__init__.py
cloudsnorkel/cdk_github_runners/_jsii/cdk-github-runners@0.14.22.jsii.tgz
cloudsnorkel_cdk_github_runners-0.14.22.dist-info/LICENSE
cloudsnorkel_cdk_github_runners-0.14.22.dist-info/METADATA
cloudsnorkel_cdk_github_runners-0.14.22.dist-info/WHEEL
cloudsnorkel_cdk_github_runners-0.14.22.dist-info/top_level.txt
cloudsnorkel_cdk_github_runners-0.14.22.dist-info/RECORD
