Metadata-Version: 2.1
Name: cloudsnorkel.cdk-github-runners
Version: 0.14.22
Summary: CDK construct to create GitHub Actions self-hosted runners. Creates ephemeral runners on demand. Easy to deploy and highly customizable.
Home-page: https://github.com/CloudSnorkel/cdk-github-runners.git
Author: Amir Szekely<amir@cloudsnorkel.com>
License: Apache-2.0
Project-URL: Source, https://github.com/CloudSnorkel/cdk-github-runners.git
Classifier: Intended Audience :: Developers
Classifier: Operating System :: OS Independent
Classifier: Programming Language :: JavaScript
Classifier: Programming Language :: Python :: 3 :: Only
Classifier: Programming Language :: Python :: 3.9
Classifier: Programming Language :: Python :: 3.10
Classifier: Programming Language :: Python :: 3.11
Classifier: Typing :: Typed
Classifier: Development Status :: 4 - Beta
Classifier: License :: OSI Approved
Requires-Python: ~=3.9
License-File: LICENSE
Requires-Dist: aws-cdk-lib <3.0.0,>=2.155.0
Requires-Dist: constructs <11.0.0,>=10.0.5
Requires-Dist: jsii <2.0.0,>=1.125.0
Requires-Dist: publication >=0.0.3
Requires-Dist: typeguard ==2.13.3
